{
    "msgParams": {
        "meta": {
            "type": "EiffelEnvironmentDefinedEvent",
            "version": "3.0.0",
            "tags": [""],
            "source": {
                "domainId": "",
                "host": "",
                "name": "",
                "uri": ""
            }
        }
    },
    "eventParams": {
        "data": {
            "name": "required",
            "version": "",
            "image": "",
            "customData": [{
                "key": "required if customData present",
                "value": "required if customData present"
            }],
            "host": {
                "name": "required if host present",
                "user": "required if host present"
            },
            "uri": ""
        },
        "links": [{
            "type": "CAUSE or CONTEXT or FLOW_CONTEXT or PREVIOUS_VERSION - optional",
            "target": "required - UUID if type is present"
        }]
    }
}